{
  "1":{
      "tag":"antimage",
      "name":"Anti-Mage",
      "alt":"Magina",
      "aliases":"am,wei",
      "alticons": ["persona1"]
  },
  "2":{
      "tag":"axe",
      "name":"Axe",
      "alt":"Mogul Khan",
      "aliases":"",
      "alticons": ["alt"]
  },
  "3":{
      "tag":"bane",
      "name":"Bane",
      "alt":"Atropos",
      "aliases":""
  },
  "4":{
      "tag":"bloodseeker",
      "name":"Bloodseeker",
      "alt":"Strygwyr",
      "aliases":"bs"
  },
  "5":{
      "tag":"crystal_maiden",
      "name":"Crystal Maiden",
      "alt":"Rylai",
      "aliases":"cm",
      "alticons": ["alt1"]
  },
  "6":{
      "tag":"drow_ranger",
      "name":"Drow Ranger",
      "alt":"Traxex",
      "aliases":""
  },
  "7":{
      "tag":"earthshaker",
      "name":"Earthshaker",
      "alt":"",
      "aliases":"es",
      "alticons": ["alt1", "alt2"]
  },
  "8":{
      "tag":"juggernaut",
      "name":"Juggernaut",
      "alt":"Yurnero",
      "aliases":"",
      "alticons": ["alt1", "alt2"]
  },
  "9":{
      "tag":"mirana",
      "name":"Mirana",
      "alt":"Priestess of the Moon",
      "aliases":"potm"
  },
  "10":{
      "tag":"morphling",
      "name":"Morphling",
      "alt":"Water",
      "aliases":""
  },
  "11":{
      "tag":"nevermore",
      "name":"Shadow Fiend",
      "alt":"Nevermore",
      "aliases":"sf,zxc,yaphets,demon",
      "alticons": ["alt"]
  },
  "12":{
      "tag":"phantom_lancer",
      "name":"Phantom Lancer",
      "alt":"Azwraith",
      "aliases":"pl"
  },
  "13":{
      "tag":"puck",
      "name":"Puck",
      "alt":"Faerie Dragon",
      "aliases":""
  },
  "14":{
      "tag":"pudge",
      "name":"Pudge",
      "alt":"Butcher",
      "aliases":"dendi",
      "alticons": ["alt1", "alt2", "persona1"]
  },
  "15":{
      "tag":"razor",
      "name":"Razor",
      "alt":"Lightning Revenant",
      "aliases":""
  },
  "16":{
      "tag":"sand_king",
      "name":"Sand King",
      "alt":"Crixalis",
      "aliases":"sk,scorpion"
  },
  "17":{
      "tag":"storm_spirit",
      "name":"Storm Spirit",
      "alt":"Raijin Thunderkeg",
      "aliases":"ss"
  },
  "18":{
      "tag":"sven",
      "name":"Sven",
      "alt":"Rogue Knight",
      "aliases":"vigil"
  },
  "19":{
      "tag":"tiny",
      "name":"Tiny",
      "alt":"Stone Giant",
      "aliases":""
  },
  "20":{
      "tag":"vengefulspirit",
      "name":"Vengeful Spirit",
      "alt":"Shendelzare",
      "aliases":"vs"
  },
  "21":{
      "tag":"windrunner",
      "name":"Windranger",
      "alt":"Lyraler",
      "aliases":"wr",
      "alticons": ["alt1", "alt2"]
  },
  "22":{
      "tag":"zuus",
      "name":"Zeus",
      "alt":"Lord of Heaven",
      "aliases":"lightning god",
      "alticons": ["alt"]
  },
  "23":{
      "tag":"kunkka",
      "name":"Kunkka",
      "alt":"Admiral",
      "aliases":"attacker"
  },
  "25":{
      "tag":"lina",
      "name":"Lina",
      "alt":"Slayer",
      "aliases":"",
      "alticons": ["alt"]
  },
  "26":{
      "tag":"lion",
      "name":"Lion",
      "alt":"Demon Witch",
      "aliases":""
  },
  "27":{
      "tag":"shadow_shaman",
      "name":"Shadow Shaman",
      "alt":"Rhasta",
      "aliases":"ss"
  },
  "28":{
      "tag":"slardar",
      "name":"Slardar",
      "alt":"Slithereen Guard",
      "aliases":""
  },
  "29":{
      "tag":"tidehunter",
      "name":"Tidehunter",
      "alt":"Leviathan",
      "aliases":""
  },
  "30":{
      "tag":"witch_doctor",
      "name":"Witch Doctor",
      "alt":"Zharvakko",
      "aliases":"wd,voodoo"
  },
  "31":{
      "tag":"lich",
      "name":"Lich",
      "alt":"Ethreain",
      "aliases":""
  },
  "32":{
      "tag":"riki",
      "name":"Riki",
      "alt":"Stealth Assassin",
      "aliases":"tahlin,rikimaru"
  },
  "33":{
      "tag":"enigma",
      "name":"Enigma",
      "alt":"Gravity Fundamental",
      "aliases":""
  },
  "34":{
      "tag":"tinker",
      "name":"Tinker",
      "alt":"Boush",
      "aliases":""
  },
  "35":{
      "tag":"sniper",
      "name":"Sniper",
      "alt":"Kardel Sharpeye",
      "aliases":""
  },
  "36":{
      "tag":"necrolyte",
      "name":"Necrophos",
      "alt":"Rotund'jere",
      "aliases":"pope of pestilence,rotundjere"
  },
  "37":{
      "tag":"warlock",
      "name":"Warlock",
      "alt":"Demnok Lannik",
      "aliases":""
  },
  "38":{
      "tag":"beastmaster",
      "name":"Beastmaster",
      "alt":"Karroch",
      "aliases":"rexxar,bm"
  },
  "39":{
      "tag":"queenofpain",
      "name":"Queen of Pain",
      "alt":"Akasha",
      "aliases":"qop",
      "alticons": ["alt1", "alt2"]
  },
  "40":{
      "tag":"venomancer",
      "name":"Venomancer",
      "alt":"Lesale Deathbringer",
      "aliases":"snake,herbalist"
  },
  "41":{
      "tag":"faceless_void",
      "name":"Faceless Void",
      "alt":"Darkterror",
      "aliases":"void,claszureme"
  },
  "42":{
      "tag":"skeleton_king",
      "name":"Wraith King",
      "alt":"Ostarion",
      "aliases":"leoric,wk,sk",
      "alticons": ["alt1", "alt2"]
  },
  "43":{
      "tag":"death_prophet",
      "name":"Death Prophet",
      "alt":"Krobelus",
      "aliases":"dp"
  },
  "44":{
      "tag":"phantom_assassin",
      "name":"Phantom Assassin",
      "alt":"Mortred",
      "aliases":"pa",
      "alticons": ["alt1"]
  },
  "45":{
      "tag":"pugna",
      "name":"Pugna",
      "alt":"Oblivion Mage",
      "aliases":""
  },
  "46":{
      "tag":"templar_assassin",
      "name":"Templar Assassin",
      "alt":"Lanaya",
      "aliases":"ta"
  },
  "47":{
      "tag":"viper",
      "name":"Viper",
      "alt":"Netherdrake",
      "aliases":""
  },
  "48":{
      "tag":"luna",
      "name":"Luna",
      "alt":"Moon Rider",
      "aliases":""
  },
  "49":{
      "tag":"dragon_knight",
      "name":"Dragon Knight",
      "alt":"Davion",
      "aliases":"slyrak,dk"
  },
  "50":{
      "tag":"dazzle",
      "name":"Dazzle",
      "alt":"Shadow Priest",
      "aliases":""
  },
  "51":{
      "tag":"rattletrap",
      "name":"Clockwerk",
      "alt":"Rattletrap",
      "aliases":""
  },
  "52":{
      "tag":"leshrac",
      "name":"Leshrac",
      "alt":"Tormented Soul",
      "aliases":""
  },
  "53":{
      "tag":"furion",
      "name":"Nature's Prophet",
      "alt":"Furion",
      "aliases":"np,rat,bulldog"
  },
  "54":{
      "tag":"life_stealer",
      "name":"Lifestealer",
      "alt":"N'aix",
      "aliases":"ghoul,ls,naix"
  },
  "55":{
      "tag":"dark_seer",
      "name":"Dark Seer",
      "alt":"Ish'Kafel",
      "aliases":"ds,ishkafel"
  },
  "56":{
      "tag":"clinkz",
      "name":"Clinkz",
      "alt":"Bone Fletcher",
      "aliases":"demon,archer,maraxiform"
  },
  "57":{
      "tag":"omniknight",
      "name":"Omniknight",
      "alt":"Purist Thunderwrath",
      "aliases":"omniscience,priest,slacks"
  },
  "58":{
      "tag":"enchantress",
      "name":"Enchantress",
      "alt":"Aiushtha",
      "aliases":""
  },
  "59":{
      "tag":"huskar",
      "name":"Huskar",
      "alt":"Sacred Warrior",
      "aliases":""
  },
  "60":{
      "tag":"night_stalker",
      "name":"Night Stalker",
      "alt":"Balanar",
      "aliases":"ns"
  },
  "61":{
      "tag":"broodmother",
      "name":"Broodmother",
      "alt":"Black Arachnia",
      "aliases":"bm,spider"
  },
  "62":{
      "tag":"bounty_hunter",
      "name":"Bounty Hunter",
      "alt":"Gondar",
      "aliases":"bh"
  },
  "63":{
      "tag":"weaver",
      "name":"Weaver",
      "alt":"Skitskurr",
      "aliases":""
  },
  "64":{
      "tag":"jakiro",
      "name":"Jakiro",
      "alt":"Twin Head Dragon",
      "aliases":"thd"
  },
  "65":{
      "tag":"batrider",
      "name":"Batrider",
      "alt":"Jin'zakk",
      "aliases":""
  },
  "66":{
      "tag":"chen",
      "name":"Chen",
      "alt":"Holy Knight",
      "aliases":""
  },
  "67":{
      "tag":"spectre",
      "name":"Spectre",
      "alt":"Mercurial",
      "aliases":"qwerty,leamare"
  },
  "68":{
      "tag":"ancient_apparition",
      "name":"Ancient Apparition",
      "alt":"Kaldr",
      "aliases":"aa"
  },
  "69":{
      "tag":"doom_bringer",
      "name":"Doom",
      "alt":"Lucifer",
      "aliases":"demon"
  },
  "70":{
      "tag":"ursa",
      "name":"Ursa",
      "alt":"Ulfsaar",
      "aliases":"bear"
  },
  "71":{
      "tag":"spirit_breaker",
      "name":"Spirit Breaker",
      "alt":"Barathrum",
      "aliases":"sb"
  },
  "72":{
      "tag":"gyrocopter",
      "name":"Gyrocopter",
      "alt":"Aurel",
      "aliases":""
  },
  "73":{
      "tag":"alchemist",
      "name":"Alchemist",
      "alt":"Razzil Darkbrew",
      "aliases":""
  },
  "74":{
      "tag":"invoker",
      "name":"Invoker",
      "alt":"Carl",
      "aliases":"carl,destroyer,arsenal magus",
      "alticons": ["persona1"]
  },
  "75":{
      "tag":"silencer",
      "name":"Silencer",
      "alt":"Nortrom",
      "aliases":""
  },
  "76":{
      "tag":"obsidian_destroyer",
      "name":"Outworld Destroyer",
      "alt":"Harbinger",
      "aliases":"od,devourer"
  },
  "77":{
      "tag":"lycan",
      "name":"Lycan",
      "alt":"Banehallow",
      "aliases":"lycanthrope,wolf"
  },
  "78":{
      "tag":"brewmaster",
      "name":"Brewmaster",
      "alt":"Mangix",
      "aliases":"brew"
  },
  "79":{
      "tag":"shadow_demon",
      "name":"Shadow Demon",
      "alt":"Cult Leader",
      "aliases":"sd"
  },
  "80":{
      "tag":"lone_druid",
      "name":"Lone Druid",
      "alt":"Sylla",
      "aliases":"bear,bulldog,ld"
  },
  "81":{
      "tag":"chaos_knight",
      "name":"Chaos Knight",
      "alt":"Armageddon Rider",
      "aliases":"fundamental"
  },
  "82":{
      "tag":"meepo",
      "name":"Meepo",
      "alt":"Geomancer",
      "aliases":""
  },
  "83":{
      "tag":"treant",
      "name":"Treant Protector",
      "alt":"Rooftrellen",
      "aliases":"tree"
  },
  "84":{
      "tag":"ogre_magi",
      "name":"Ogre Magi",
      "alt":"Aggron Stonebreak",
      "aliases":"",
      "alticons": ["alt1", "alt2"]
  },
  "85":{
      "tag":"undying",
      "name":"Undying",
      "alt":"Almighty Dirge",
      "aliases":"zombie"
  },
  "86":{
      "tag":"rubick",
      "name":"Rubick",
      "alt":"Grand Magus",
      "aliases":"gm",
      "alticons": ["alt"]
  },
  "87":{
      "tag":"disruptor",
      "name":"Disruptor",
      "alt":"Stormcrafter",
      "aliases":""
  },
  "88":{
      "tag":"nyx_assassin",
      "name":"Nyx Assassin",
      "alt":"Zealot Scarab",
      "aliases":""
  },
  "89":{
      "tag":"naga_siren",
      "name":"Naga Siren",
      "alt":"Slithice",
      "aliases":"slithereen"
  },
  "90":{
      "tag":"keeper_of_the_light",
      "name":"Keeper of the Light",
      "alt":"Ezalor",
      "aliases":"kotl,fundamental"
  },
  "91":{
      "tag":"wisp",
      "name":"Io",
      "alt":"Wisp",
      "aliases":"fundamental"
  },
  "92":{
      "tag":"visage",
      "name":"Visage",
      "alt":"Necro'lic",
      "aliases":""
  },
  "93":{
      "tag":"slark",
      "name":"Slark",
      "alt":"Nightcrawler",
      "aliases":""
  },
  "94":{
      "tag":"medusa",
      "name":"Medusa",
      "alt":"Gorgon",
      "aliases":""
  },
  "95":{
      "tag":"troll_warlord",
      "name":"Troll Warlord",
      "alt":"Jah'rakal",
      "aliases":""
  },
  "96":{
      "tag":"centaur",
      "name":"Centaur Warrunner",
      "alt":"Bradwarden",
      "aliases":""
  },
  "97":{
      "tag":"magnataur",
      "name":"Magnus",
      "alt":"Magnoceros",
      "aliases":""
  },
  "98":{
      "tag":"shredder",
      "name":"Timbersaw",
      "alt":"Rizzrack",
      "aliases":""
  },
  "99":{
      "tag":"bristleback",
      "name":"Bristleback",
      "alt":"Rigwarl",
      "aliases":"bb"
  },
  "100":{
      "tag":"tusk",
      "name":"Tusk",
      "alt":"Ymir",
      "aliases":""
  },
  "101":{
      "tag":"skywrath_mage",
      "name":"Skywrath Mage",
      "alt":"Dragonus",
      "aliases":"sky"
  },
  "102":{
      "tag":"abaddon",
      "name":"Abaddon",
      "alt":"Lord of Avernus",
      "aliases":""
  },
  "103":{
      "tag":"elder_titan",
      "name":"Elder Titan",
      "alt":"Creator",
      "aliases":"et"
  },
  "104":{
      "tag":"legion_commander",
      "name":"Legion Commander",
      "alt":"Tresdin",
      "aliases":"lc",
      "alticons": ["alt"]
  },
  "105":{
      "tag":"techies",
      "name":"Techies",
      "alt":"Squee, Spleen and Spoon",
      "aliases":"miner",
      "alticons": ["alt"]
  },
  "106":{
      "tag":"ember_spirit",
      "name":"Ember Spirit",
      "alt":"Xin",
      "aliases":"ana,es"
  },
  "107":{
      "tag":"earth_spirit",
      "name":"Earth Spirit",
      "alt":"Kaolin",
      "aliases":"es,jerax"
  },
  "108":{
      "tag":"abyssal_underlord",
      "name":"Underlord",
      "alt":"Vrogros",
      "aliases":"pitlord"
  },
  "109":{
      "tag":"terrorblade",
      "name":"Terrorblade",
      "alt":"Demon Marauder",
      "aliases":"demon",
      "alticons": ["alt"]
  },
  "110":{
      "tag":"phoenix",
      "name":"Phoenix",
      "alt":"Star",
      "aliases":"firebird,sun"
  },
  "111":{
      "tag":"oracle",
      "name":"Oracle",
      "alt":"Nerif",
      "aliases":""
  },
  "112":{
      "tag":"winter_wyvern",
      "name":"Winter Wyvern",
      "alt":"Auroth",
      "aliases":"ww"
  },
  "113":{
      "tag":"arc_warden",
      "name":"Arc Warden",
      "alt":"Zet",
      "aliases":"ancient,aw"
  },
  "114":{
      "tag":"monkey_king",
      "name":"Monkey King",
      "alt":"Sun Wukong",
      "aliases":"mk",
      "alticons": ["alt"]
  },
  "119":{
      "tag":"dark_willow",
      "name":"Dark Willow",
      "alt":"Mireska",
      "aliases":"sylph,fairy,dw"
  },
  "120":{
      "tag":"pangolier",
      "name":"Pangolier",
      "alt":"Donte",
      "aliases":"armodillo"
  },
  "121":{
      "tag": "grimstroke",
      "name": "Grimstroke",
      "alt":"Ascended One",
      "aliases":"ashkavor"
  },
  "123":{
      "tag": "hoodwink",
      "name": "Hoodwink",
      "alt":"Sharpshooter",
      "aliases":"squirrel,rat,mouse,mistwoods"
  },
  "126":{
      "tag":"void_spirit",
      "name":"Void Spirit",
      "alt":"Inai",
      "aliases":"vs"
  },
  "128":{
      "tag":"snapfire",
      "name":"Snapfire",
      "alt":"Beatrix",
      "aliases":"granny"
  },
  "129":{
      "tag":"mars",
      "name":"Mars",
      "alt":"First Son of Heaven",
      "aliases":"ares,god of war"
  },
  "135":{
      "tag":"dawnbreaker",
      "name":"Dawnbreaker",
      "alt":"Valora",
      "aliases":"battlemaiden,valkyrie,db"
  },
  "136":{
    "tag":"marci",
    "name":"Marci",
    "alt":"Sidekick",
    "aliases":"fighter,sidekick"
  }
}
